LICENSE
simbsig/base/__init__.py
simbsig/base/_base.py
simbsig/cluster/MiniBatchKMeans.py
simbsig/cluster/__init__.py
simbsig/decomposition/PCA.py
simbsig/decomposition/__init__.py
simbsig/neighbors/KNeighborsClassifier.py
simbsig/neighbors/KNeighborsRegressor.py
simbsig/neighbors/NearestNeighbors.py
simbsig/neighbors/RadiusNeighborsClassifier.py
simbsig/neighbors/RadiusNeighborsRegressor.py
simbsig/neighbors/__init__.py
simbsig/utils/datasets.py
simbsig/utils/metrics.py
simbsig/utils/utils.py
simbsig-0.1.2.dist-info/LICENSE
simbsig-0.1.2.dist-info/WHEEL
simbsig-0.1.2.dist-info/METADATA
simbsig-0.1.2.dist-info/RECORD
