Metadata-Version: 2.1
Name: simbsig
Version: 0.1.2
Summary: A python package for out-of-core similarity search and dimensionality reduction
Home-page: https://github.com/BorgwardtLab/simbsig
License: BSD-3-Clause
Keywords: similarity search,kmeans,knn,nearest neighbors,gpu,pca
Author: Eljas Roellin
Author-email: roelline@student.ethz.ch
Requires-Python: >=3.8,<4.0
Classifier: License :: OSI Approved :: BSD License
Classifier: Programming Language :: Python :: 3
Classifier: Programming Language :: Python :: 3.10
Classifier: Programming Language :: Python :: 3.8
Classifier: Programming Language :: Python :: 3.9
Requires-Dist: h5py (>=3.7.0,<4.0.0)
Requires-Dist: numpy (>=1.22.0,<2.0.0)
Requires-Dist: scikit-learn (>=1.1.0,<2.0.0)
Requires-Dist: torch (>=1.9.0,<2.0.0)
Requires-Dist: tqdm (>=4.64.0,<5.0.0)
Project-URL: Repository, https://github.com/BorgwardtLab/simbsig
